{"index":21397256,"examples_quantiles":[{"quantile_name":"Top Activations","examples":[{"tokens_acts_list":[0.0,0.0,0.0,0.0,0.0,0.0,0.0,0.0,0.0,0.0,0.0,0.0,0.0,0.0,0.0,0.0,0.0,0.0,0.0,0.21,1.0,0.0,0.0,0.0,0.0,0.0,0.0,0.0,0.0,0.0,0.0,0.0,0.0,0.0,0.0,0.0,0.0,0.0,0.0,0.0,0.0],"train_token_ind":20,"is_repeated_datapoint":false,"tokens":["required"," -"," around"," ","25"," ","euros",".","\u23ce\u23ce","Although"," you"," can"," save"," a"," bit"," of"," money"," by"," buying"," platinum"," in"," large"," quantities"," and"," thus"," at"," a"," discount",","," the"," community"," re","acts"," neg","atively"," to"," the"," price"," information"," in"," the"]},{"tokens_acts_list":[0.0,0.0,0.0,0.0,0.0,0.0,0.0,0.0,0.0,0.0,0.0,0.0,0.0,0.0,0.0,0.0,0.0,0.0,0.0,0.25,0.95,0.0,0.0,0.0,0.0,0.0,0.0,0.0,0.0,0.0,0.0,0.0,0.0,0.0,0.0,0.0,0.0,0.0,0.0,0.0,0.0],"train_token_ind":20,"is_repeated_datapoint":false,"tokens":["various"," locations"," throughout"," Berlin",","," just"," like"," the"," Special"," Olympics"," Festival"," that"," accompan","ies"," the"," NAME","_","2",","," offering"," a"," wide"," variety"," of"," inclusive"," and"," cultural"," activities"," and"," events","."," From"," June"," ","17"," ","to"," ","25",","," over"]},{"tokens_acts_list":[0.28,0.0,0.0,0.0,0.0,0.0,0.0,0.0,0.0,0.0,0.0,0.0,0.0,0.0,0.0,0.0,0.0,0.0,0.0,0.0,0.88,0.0,0.33,0.0,0.0,0.0,0.0,0.0,0.0,0.65,0.0,0.43,0.0,0.0,0.0,0.0,0.0,0.0,0.5,0.0,0.24],"train_token_ind":20,"is_repeated_datapoint":false,"tokens":["|"," fine"," |"," co","arse"," |"," ","\u23ce","|"," hard","ness"," |"," soft"," |"," hard"," |"," ","\u23ce","|"," length"," |"," short"," |"," long"," |"," ","\u23ce","|"," magnitude"," |"," small"," |"," large"," |"," ","\u23ce","|"," mass"," |"," small"," |"]},{"tokens_acts_list":[0.0,0.0,0.0,0.0,0.0,0.0,0.0,0.0,0.0,0.0,0.0,0.0,0.0,0.0,0.0,0.0,0.0,0.0,0.0,0.0,0.88,0.06,0.0,0.0,0.0,0.0,0.0,0.0,0.0,0.0,0.0,0.0,0.0,0.0,0.0,0.0,0.0,0.0,0.0,0.0,0.0],"train_token_ind":20,"is_repeated_datapoint":false,"tokens":["."," NAME","_","2"," ","dra","ait"," NAME","_","2"," ","om"," en"," g","rij","pt"," naar"," het"," mes","."," Een"," kor","te"," uit","bar","sting"," van"," intense"," p","ijn"," l","aat"," NAME","_","2"," ","naar"," a","dem"," happen","."]},{"tokens_acts_list":[0.0,0.0,0.0,0.0,0.0,0.0,0.0,0.0,0.0,0.0,0.0,0.0,0.0,0.0,0.0,0.0,0.0,0.0,0.0,0.43,0.82,0.0,0.0,0.0,0.0,0.0,0.0,0.0,0.0,0.0,0.0,0.0,0.0,0.0,0.0,0.0,0.0,0.0,0.0,0.0,0.0],"train_token_ind":20,"is_repeated_datapoint":false,"tokens":[","," had"," problems"," that"," they"," require"," severe"," conditions"," for"," heat"," treatment",","," i",".","e","."," a"," high"," treatment"," and"," a"," long"," period"," of"," heating",","," and"," that"," matters"," in","sol","uble"," in"," an"," organic"," sol","vent"," are"," formed"," which"," cause"]},{"tokens_acts_list":[0.0,0.0,0.0,0.0,0.0,0.55,0.76,0.0,0.0,0.0,0.0,0.0,0.0,0.0,0.0,0.0,0.0,0.0,0.0,0.18,0.8,0.0,0.0,0.0,0.0,0.0,0.0,0.0,0.0,0.0,0.0,0.0,0.0,0.0,0.0,0.0,0.0,0.0,0.0,0.0,0.0],"train_token_ind":20,"is_repeated_datapoint":false,"tokens":[";"," if"," you"," use"," division",","," a"," large"," total",","," divided"," by"," ","1",".","3"," ","billion",","," will"," become"," a"," small"," number"," .","This"," is"," something"," many"," foreign","ers"," do"," not"," understand","."," ###","Question",":","Which"," of"," the"]},{"tokens_acts_list":[0.0,0.0,0.0,0.0,0.0,0.0,0.0,0.0,0.0,0.0,0.0,0.0,0.0,0.0,0.0,0.0,0.0,0.0,0.0,0.0,0.79,0.0,0.0,0.0,0.0,0.0,0.0,0.0,0.0,0.0,0.0,0.0,0.0,0.0,0.0,0.0,0.0,0.0,0.0,0.0,0.0],"train_token_ind":20,"is_repeated_datapoint":false,"tokens":["the"," heat"," treatment"," temperature"," and"," duration"," in"," the"," drive","-","in"," diff","usion"," method","."," However",","," such"," high"," temperature"," and"," long"," heat"," treatment"," time"," create"," a"," problem"," in"," that"," the"," junction"," depth"," of"," the"," em","itter"," region"," becomes"," large",","]},{"tokens_acts_list":[0.0,0.0,0.0,0.0,0.0,0.0,0.0,0.0,0.0,0.0,0.0,0.0,0.07,0.5,0.0,0.28,0.53,0.0,0.0,0.47,0.79,0.0,0.24,0.62,0.0,0.0,0.0,0.0,0.0,0.0,0.0,0.0,0.0,0.0,0.0,0.0,0.0,0.0,0.0,0.0,0.0],"train_token_ind":20,"is_repeated_datapoint":false,"tokens":["may"," not"," be"," no","tic","able"," by"," the"," end"," user",","," while"," either"," a"," small"," area",","," large"," magnitude"," or"," a"," large"," area",","," small"," magnitude"," def","ect"," might"," be"," easily"," seen","."," Small"," area"," def","ects"," are"," typically"," called"," local"]},{"tokens_acts_list":[0.0,0.0,0.0,0.0,0.0,0.0,0.0,0.0,0.0,0.0,0.0,0.0,0.0,0.0,0.0,0.0,0.0,0.0,0.0,0.13,0.77,0.0,0.0,0.0,0.0,0.0,0.0,0.0,0.0,0.0,0.0,0.0,0.0,0.0,0.0,0.0,0.0,0.0,0.0,0.0,0.0],"train_token_ind":20,"is_repeated_datapoint":false,"tokens":["pruss","iens",","," le"," pr","over","be"," qui"," ass","ure"," que"," \u00ab"," les"," pet","its"," eff","ets"," eng","end","rent"," les"," grandes"," causes","\u00bb"," est"," to","uj","ours"," v","rai",";"," et"," cette"," fois"," il"," l","'","est"," cru","ellement","."]},{"tokens_acts_list":[0.0,0.0,0.0,0.0,0.0,0.0,0.0,0.0,0.0,0.0,0.13,0.14,0.0,0.0,0.0,0.0,0.0,0.0,0.0,0.55,0.76,0.0,0.0,0.0,0.0,0.0,0.0,0.0,0.0,0.0,0.0,0.0,0.0,0.18,0.8,0.0,0.0,0.0,0.0,0.0,0.0],"train_token_ind":20,"is_repeated_datapoint":false,"tokens":["ied"," by"," ","1",".","3"," ","billion",","," will"," become"," a"," big"," problem",";"," if"," you"," use"," division",","," a"," large"," total",","," divided"," by"," ","1",".","3"," ","billion",","," will"," become"," a"," small"," number"," .","This"," is"]},{"tokens_acts_list":[0.0,0.0,0.0,0.0,0.0,0.0,0.0,0.13,0.0,0.0,0.0,0.0,0.0,0.06,0.0,0.0,0.0,0.0,0.0,0.22,0.76,0.0,0.0,0.0,0.0,0.0,0.0,0.0,0.0,0.0,0.0,0.0,0.0,0.15,0.0,0.0,0.0,0.0,0.2,0.12,0.62],"train_token_ind":20,"is_repeated_datapoint":false,"tokens":[".","3"," ","billion",","," which"," is"," a"," big"," number",","," can"," become"," a"," small"," problem"," if"," multipl","ied"," or"," a"," large"," problem"," if"," divided","."," This"," is"," similar"," to"," the"," idea"," that"," many"," people"," collecting"," fir","ewood"," can"," result"," in"]},{"tokens_acts_list":[0.0,0.0,0.0,0.0,0.0,0.0,0.0,0.0,0.0,0.0,0.0,0.0,0.0,0.0,0.0,0.0,0.0,0.0,0.0,0.0,0.73,0.0,0.0,0.0,0.0,0.0,0.0,0.0,0.0,0.0,0.0,0.0,0.0,0.0,0.0,0.0,0.0,0.0,0.0,0.0,0.0],"train_token_ind":20,"is_repeated_datapoint":false,"tokens":[".","\u2191"," Accordingly",","," the"," multi","-","view"," video"," will"," require"," a"," large"," storage"," space"," to"," store"," and","/","or"," a"," high"," bandwidth"," to"," transm","it","."," Therefore",","," multi","-","view"," video"," coding"," techniques"," have"," been"," developed"," in"," the"," field"]},{"tokens_acts_list":[0.0,0.0,0.0,0.0,0.18,0.0,0.0,0.0,0.0,0.0,0.0,0.0,0.54,0.0,0.0,0.0,0.0,0.12,0.0,0.0,0.72,0.0,0.0,0.0,0.0,0.0,0.0,0.0,0.0,0.0,0.0,0.0,0.0,0.0,0.0,0.0,0.0,0.0,0.0,0.0,0.0],"train_token_ind":20,"is_repeated_datapoint":false,"tokens":["|","\u23ce","|"," density"," |"," sparse"," |"," dense"," |","\u23ce","|"," depth"," |"," shallow"," |"," deep"," |","\u23ce","|"," distance"," |"," near"," |"," far"," |"," ","\u23ce","|"," electric"," conduct","ivity"," |"," low"," |"," high"," |","\u23ce","|"," flexibility"," |"," rigid"]},{"tokens_acts_list":[0.0,0.0,0.0,0.0,0.0,0.0,0.0,0.0,0.0,0.0,0.0,0.0,0.0,0.0,0.0,0.0,0.0,0.0,0.38,0.66,0.72,0.0,0.0,0.0,0.0,0.0,0.0,0.0,0.0,0.0,0.0,0.0,0.0,0.0,0.0,0.0,0.0,0.0,0.0,0.0,0.0],"train_token_ind":20,"is_repeated_datapoint":false,"tokens":["trop","f","end","osen"," zwe","imal"," t\u00e4","glich","\u23ce\u23ce","\u2191"," S\u00fc","\u00df","hol","z","w","ur","zel",":"," ","10"," ","kleine","\u2191"," Trop","fen"," (","keine","\u2191"," Trop","f","end","osen",")"," zwe","imal"," t\u00e4","glich"," (","zwei","\u2191"," Wo"]},{"tokens_acts_list":[0.0,0.0,0.0,0.0,0.0,0.0,0.0,0.0,0.0,0.0,0.0,0.0,0.0,0.0,0.0,0.0,0.0,0.0,0.0,0.0,0.71,0.0,0.0,0.0,0.0,0.0,0.0,0.0,0.0,0.0,0.0,0.0,0.0,0.0,0.0,0.0,0.0,0.0,0.0,0.0,0.0],"train_token_ind":20,"is_repeated_datapoint":false,"tokens":["with"," being"," f","uzz"," tests"," on"," what","\u23ce"," happens"," when"," you"," have"," a"," whole"," bunch"," of"," something"," (","long"," strings",","," many"," items",")","\u23ce","loaded"," into"," a"," control",".","\u2191"," Normally"," the"," control"," library"," itself"," takes"," care"," of"," that","\u23ce"]},{"tokens_acts_list":[0.0,0.0,0.0,0.0,0.0,0.0,0.0,0.0,0.42,0.0,0.0,0.0,0.0,0.0,0.0,0.0,0.08,0.0,0.0,0.0,0.71,0.0,0.0,0.0,0.0,0.0,0.0,0.0,0.0,0.0,0.0,0.0,0.0,0.0,0.0,0.0,0.0,0.0,0.0,0.0,0.0],"train_token_ind":20,"is_repeated_datapoint":false,"tokens":["great"," and"," the"," size"," of"," the"," transfer"," sheet"," is"," small",","," the"," scanning"," speed"," is"," slow"," and"," the"," scanning"," stroke"," is"," short","."," For"," this"," reason",","," heat"," generated"," by"," the"," lamp"," may"," locally"," ov","erh","eat"," the"," original"," base",","]}]},{"quantile_name":"Subsample Interval 0","examples":[{"tokens_acts_list":[0.0,0.0,0.0,0.0,0.0,0.0,0.0,0.0,0.0,0.0,0.0,0.0,0.0,0.0,0.0,0.0,0.0,0.0,0.0,0.21,1.0,0.0,0.0,0.0,0.0,0.0,0.0,0.0,0.0,0.0,0.0,0.0,0.0,0.0,0.0,0.0,0.0,0.0,0.0,0.0,0.0],"train_token_ind":20,"is_repeated_datapoint":true,"tokens":["required"," -"," around"," ","25"," ","euros",".","\u23ce\u23ce","Although"," you"," can"," save"," a"," bit"," of"," money"," by"," buying"," platinum"," in"," large"," quantities"," and"," thus"," at"," a"," discount",","," the"," community"," re","acts"," neg","atively"," to"," the"," price"," information"," in"," the"]},{"tokens_acts_list":[0.0,0.0,0.0,0.0,0.0,0.0,0.0,0.0,0.0,0.0,0.0,0.0,0.0,0.0,0.0,0.0,0.0,0.0,0.0,0.25,0.95,0.0,0.0,0.0,0.0,0.0,0.0,0.0,0.0,0.0,0.0,0.0,0.0,0.0,0.0,0.0,0.0,0.0,0.0,0.0,0.0],"train_token_ind":20,"is_repeated_datapoint":true,"tokens":["various"," locations"," throughout"," Berlin",","," just"," like"," the"," Special"," Olympics"," Festival"," that"," accompan","ies"," the"," NAME","_","2",","," offering"," a"," wide"," variety"," of"," inclusive"," and"," cultural"," activities"," and"," events","."," From"," June"," ","17"," ","to"," ","25",","," over"]},{"tokens_acts_list":[0.28,0.0,0.0,0.0,0.0,0.0,0.0,0.0,0.0,0.0,0.0,0.0,0.0,0.0,0.0,0.0,0.0,0.0,0.0,0.0,0.88,0.0,0.33,0.0,0.0,0.0,0.0,0.0,0.0,0.65,0.0,0.43,0.0,0.0,0.0,0.0,0.0,0.0,0.5,0.0,0.24],"train_token_ind":20,"is_repeated_datapoint":true,"tokens":["|"," fine"," |"," co","arse"," |"," ","\u23ce","|"," hard","ness"," |"," soft"," |"," hard"," |"," ","\u23ce","|"," length"," |"," short"," |"," long"," |"," ","\u23ce","|"," magnitude"," |"," small"," |"," large"," |"," ","\u23ce","|"," mass"," |"," small"," |"]},{"tokens_acts_list":[0.0,0.0,0.0,0.0,0.0,0.0,0.0,0.0,0.0,0.0,0.0,0.0,0.0,0.0,0.0,0.0,0.0,0.0,0.0,0.0,0.88,0.06,0.0,0.0,0.0,0.0,0.0,0.0,0.0,0.0,0.0,0.0,0.0,0.0,0.0,0.0,0.0,0.0,0.0,0.0,0.0],"train_token_ind":20,"is_repeated_datapoint":true,"tokens":["."," NAME","_","2"," ","dra","ait"," NAME","_","2"," ","om"," en"," g","rij","pt"," naar"," het"," mes","."," Een"," kor","te"," uit","bar","sting"," van"," intense"," p","ijn"," l","aat"," NAME","_","2"," ","naar"," a","dem"," happen","."]}]},{"quantile_name":"Subsample Interval 1","examples":[{"tokens_acts_list":[0.28,0.0,0.0,0.0,0.0,0.0,0.0,0.0,0.0,0.0,0.0,0.0,0.0,0.0,0.0,0.0,0.0,0.0,0.0,0.0,0.85,0.0,0.33,0.0,0.0,0.0,0.0,0.0,0.0,0.64,0.0,0.44,0.0,0.0,0.0,0.0,0.0,0.0,0.5,0.0,0.23],"train_token_ind":20,"is_repeated_datapoint":true,"tokens":["|"," fine"," |"," co","arse"," |"," ","\u23ce","|"," hard","ness"," |"," soft"," |"," hard"," |"," ","\u23ce","|"," length"," |"," short"," |"," long"," |"," ","\u23ce","|"," magnitude"," |"," small"," |"," large"," |"," ","\u23ce","|"," mass"," |"," small"," |"]},{"tokens_acts_list":[0.0,0.0,0.0,0.0,0.0,0.0,0.0,0.0,0.0,0.0,0.0,0.0,0.0,0.0,0.0,0.0,0.0,0.0,0.0,0.43,0.82,0.0,0.0,0.0,0.0,0.0,0.0,0.0,0.0,0.0,0.0,0.0,0.0,0.0,0.0,0.0,0.0,0.0,0.0,0.0,0.0],"train_token_ind":20,"is_repeated_datapoint":true,"tokens":[","," had"," problems"," that"," they"," require"," severe"," conditions"," for"," heat"," treatment",","," i",".","e","."," a"," high"," treatment"," and"," a"," long"," period"," of"," heating",","," and"," that"," matters"," in","sol","uble"," in"," an"," organic"," sol","vent"," are"," formed"," which"," cause"]},{"tokens_acts_list":[0.0,0.0,0.0,0.0,0.0,0.55,0.76,0.0,0.0,0.0,0.0,0.0,0.0,0.0,0.0,0.0,0.0,0.0,0.0,0.18,0.8,0.0,0.0,0.0,0.0,0.0,0.0,0.0,0.0,0.0,0.0,0.0,0.0,0.0,0.0,0.0,0.0,0.0,0.0,0.0,0.0],"train_token_ind":20,"is_repeated_datapoint":true,"tokens":[";"," if"," you"," use"," division",","," a"," large"," total",","," divided"," by"," ","1",".","3"," ","billion",","," will"," become"," a"," small"," number"," .","This"," is"," something"," many"," foreign","ers"," do"," not"," understand","."," ###","Question",":","Which"," of"," the"]},{"tokens_acts_list":[0.0,0.0,0.0,0.0,0.0,0.0,0.0,0.0,0.0,0.0,0.0,0.0,0.0,0.0,0.0,0.0,0.0,0.0,0.0,0.0,0.79,0.0,0.0,0.0,0.0,0.0,0.0,0.0,0.0,0.0,0.0,0.0,0.0,0.0,0.0,0.0,0.0,0.0,0.0,0.0,0.0],"train_token_ind":20,"is_repeated_datapoint":true,"tokens":["the"," heat"," treatment"," temperature"," and"," duration"," in"," the"," drive","-","in"," diff","usion"," method","."," However",","," such"," high"," temperature"," and"," long"," heat"," treatment"," time"," create"," a"," problem"," in"," that"," the"," junction"," depth"," of"," the"," em","itter"," region"," becomes"," large",","]},{"tokens_acts_list":[0.0,0.0,0.0,0.0,0.0,0.0,0.0,0.0,0.0,0.0,0.0,0.0,0.07,0.5,0.0,0.28,0.53,0.0,0.0,0.47,0.79,0.0,0.24,0.62,0.0,0.0,0.0,0.0,0.0,0.0,0.0,0.0,0.0,0.0,0.0,0.0,0.0,0.0,0.0,0.0,0.0],"train_token_ind":20,"is_repeated_datapoint":true,"tokens":["may"," not"," be"," no","tic","able"," by"," the"," end"," user",","," while"," either"," a"," small"," area",","," large"," magnitude"," or"," a"," large"," area",","," small"," magnitude"," def","ect"," might"," be"," easily"," seen","."," Small"," area"," def","ects"," are"," typically"," called"," local"]}]},{"quantile_name":"Subsample Interval 2","examples":[{"tokens_acts_list":[0.0,0.0,0.0,0.0,0.0,0.0,0.0,0.0,0.42,0.0,0.0,0.0,0.0,0.0,0.0,0.0,0.08,0.0,0.0,0.0,0.71,0.0,0.0,0.0,0.0,0.0,0.0,0.0,0.0,0.0,0.0,0.0,0.0,0.0,0.0,0.0,0.0,0.0,0.0,0.0,0.0],"train_token_ind":20,"is_repeated_datapoint":true,"tokens":["great"," and"," the"," size"," of"," the"," transfer"," sheet"," is"," small",","," the"," scanning"," speed"," is"," slow"," and"," the"," scanning"," stroke"," is"," short","."," For"," this"," reason",","," heat"," generated"," by"," the"," lamp"," may"," locally"," ov","erh","eat"," the"," original"," base",","]},{"tokens_acts_list":[0.0,0.0,0.0,0.0,0.17,0.0,0.0,0.0,0.0,0.0,0.0,0.0,0.54,0.0,0.0,0.0,0.0,0.0,0.0,0.0,0.71,0.0,0.0,0.0,0.0,0.0,0.0,0.0,0.0,0.0,0.0,0.0,0.0,0.0,0.0,0.0,0.0,0.0,0.0,0.0,0.0],"train_token_ind":20,"is_repeated_datapoint":true,"tokens":["|","\u23ce","|"," density"," |"," sparse"," |"," dense"," |","\u23ce","|"," depth"," |"," shallow"," |"," deep"," |","\u23ce","|"," distance"," |"," near"," |"," far"," |"," ","\u23ce","|"," electric"," conduct","ivity"," |"," low"," |"," high"," |","\u23ce","|"," flexibility"," |"," rigid"]},{"tokens_acts_list":[0.0,0.0,0.0,0.07,0.0,0.0,0.0,0.0,0.0,0.0,0.0,0.5,0.0,0.0,0.0,0.0,0.0,0.0,0.0,0.0,0.7,0.0,0.26,0.0,0.0,0.0,0.0,0.0,0.44,0.0,0.0,0.0,0.0,0.0,0.0,0.0,0.0,0.63,0.0,0.0,0.0],"train_token_ind":20,"is_repeated_datapoint":false,"tokens":["thermal"," conduct","ivity"," |"," low"," |"," high"," |","\u23ce","|"," thickness"," |"," thin"," |"," thick"," |"," ","\u23ce","|"," volume"," |"," small"," |"," large"," |","\u23ce","|"," weight"," |"," light"," |"," heavy"," |"," ","\u23ce","|"," width"," |"," narrow"," |"," wide"]}]},{"quantile_name":"Subsample Interval 3","examples":[{"tokens_acts_list":[0.0,0.0,0.0,0.0,0.0,0.0,0.0,0.0,0.0,0.0,0.0,0.0,0.0,0.0,0.0,0.0,0.0,0.0,0.0,0.19,0.62,0.0,0.0,0.0,0.0,0.0,0.0,0.0,0.0,0.0,0.0,0.0,0.0,0.0,0.0,0.0,0.0,0.0,0.0,0.0,0.0],"train_token_ind":20,"is_repeated_datapoint":false,"tokens":[",","\u2191"," Salv","atore"," (","\u2191","Tot","\u00f2","),"," was"," the"," supreme"," head"," of"," the","\u2191"," Sic","ilian"," ma","fia"," for"," a"," long"," time",".","  ","This"," embl","ematic"," case"," is"," not"," an"," isolated"," one",","," but"," also"," concerns"," other"," people"]},{"tokens_acts_list":[0.0,0.0,0.0,0.69,0.0,0.23,0.0,0.0,0.0,0.0,0.0,0.43,0.0,0.0,0.0,0.0,0.0,0.0,0.0,0.0,0.61,0.0,0.0,0.0,0.0,0.0,0.0,0.0,0.0,0.0,0.0,0.0,0.0,0.0,0.0,0.0,0.0,0.0,0.0,0.0,0.0],"train_token_ind":20,"is_repeated_datapoint":false,"tokens":["\u23ce","|"," volume"," |"," small"," |"," large"," |","\u23ce","|"," weight"," |"," light"," |"," heavy"," |"," ","\u23ce","|"," width"," |"," narrow"," |"," wide"," |"," ","\u23ce","|"," location"," |"," in"," |"," out"," |","\u23ce","|"," location"," |"," up"," |"," down"]},{"tokens_acts_list":[0.0,0.48,0.0,0.0,0.0,0.0,0.0,0.0,0.0,0.0,0.0,0.42,0.0,0.0,0.0,0.0,0.0,0.0,0.0,0.0,0.6,0.0,0.0,0.0,0.0,0.0,0.0,0.0,0.0,0.0,0.0,0.0,0.0,0.0,0.0,0.0,0.0,0.0,0.0,0.37,0.0],"train_token_ind":20,"is_repeated_datapoint":false,"tokens":["sound"," |"," quiet"," |"," loud"," |"," ","\u23ce","|"," sound"," pitch"," |"," low"," |"," high"," |"," ","\u23ce","|"," speed"," |"," slow"," |"," fast"," |"," ","\u23ce","|"," stability"," |"," unst","able"," |"," stable"," |"," ","\u23ce","|"," strength"," |"," weak"]},{"tokens_acts_list":[0.0,0.5,0.0,0.24,0.0,0.0,0.0,0.0,0.0,0.0,0.0,0.0,0.0,0.0,0.0,0.0,0.0,0.0,0.0,0.0,0.6,0.0,0.0,0.0,0.0,0.0,0.0,0.0,0.0,0.21,0.0,0.0,0.0,0.0,0.0,0.0,0.0,0.0,0.3,0.0,0.0],"train_token_ind":20,"is_repeated_datapoint":false,"tokens":["mass"," |"," small"," |"," large"," |"," ","\u23ce","|"," od","or"," |"," weak"," |"," strong"," |"," ","\u23ce","|"," pressure"," |"," low"," |"," high"," |"," ","\u23ce","|"," resistance"," |"," low"," |"," high"," |"," ","\u23ce","|"," shape"," |"," round"," |"]}]},{"quantile_name":"Subsample Interval 4","examples":[{"tokens_acts_list":[0.0,0.0,0.0,0.0,0.0,0.0,0.0,0.0,0.0,0.0,0.0,0.0,0.0,0.0,0.0,0.0,0.0,0.34,0.0,0.31,0.5,0.0,0.0,0.0,0.0,0.0,0.0,0.0,0.0,0.0,0.0,0.0,0.0,0.0,0.0,0.0,0.0,0.0,0.0,0.0,0.0],"train_token_ind":20,"is_repeated_datapoint":false,"tokens":[" ","or"," more"," or"," ","3",":","1"," ","or"," more",","," in"," other"," words"," a"," wide"," and"," shallow"," or"," a"," narrow"," and"," deep"," tr","ench"," being"," realized",".","<EOT>","Field"," of"," the","\u2191"," Invention","\u23ce"," This"," invention"," relates"," to"," the"]},{"tokens_acts_list":[0.0,0.0,0.0,0.0,0.0,0.0,0.0,0.0,0.0,0.0,0.0,0.0,0.07,0.0,0.0,0.0,0.0,0.0,0.0,0.0,0.5,0.0,0.0,0.0,0.0,0.0,0.0,0.0,0.0,0.7,0.0,0.26,0.0,0.0,0.0,0.0,0.0,0.44,0.0,0.0,0.0],"train_token_ind":20,"is_repeated_datapoint":false,"tokens":["texture"," |"," smooth"," |"," rough"," |"," ","\u23ce","|"," thermal"," conduct","ivity"," |"," low"," |"," high"," |","\u23ce","|"," thickness"," |"," thin"," |"," thick"," |"," ","\u23ce","|"," volume"," |"," small"," |"," large"," |","\u23ce","|"," weight"," |"," light"," |"," heavy"]},{"tokens_acts_list":[0.0,0.0,0.85,0.0,0.33,0.0,0.0,0.0,0.0,0.0,0.0,0.64,0.0,0.44,0.0,0.0,0.0,0.0,0.0,0.0,0.5,0.0,0.23,0.0,0.0,0.0,0.0,0.0,0.0,0.0,0.0,0.0,0.0,0.0,0.0,0.0,0.0,0.0,0.0,0.57,0.0],"train_token_ind":20,"is_repeated_datapoint":false,"tokens":["|"," length"," |"," short"," |"," long"," |"," ","\u23ce","|"," magnitude"," |"," small"," |"," large"," |"," ","\u23ce","|"," mass"," |"," small"," |"," large"," |"," ","\u23ce","|"," od","or"," |"," weak"," |"," strong"," |"," ","\u23ce","|"," pressure"," |"," low"]},{"tokens_acts_list":[0.0,0.0,0.0,0.0,0.0,0.0,0.0,0.0,0.0,0.0,0.0,0.0,0.0,0.0,0.0,0.0,0.0,0.0,0.0,0.23,0.5,0.0,0.0,0.0,0.0,0.0,0.0,0.0,0.0,0.0,0.0,0.0,0.0,0.0,0.0,0.0,0.0,0.0,0.0,0.0,0.0],"train_token_ind":20,"is_repeated_datapoint":false,"tokens":["high"," water"," content"," requires"," long"," d","rying"," cycles","."," Thus",","," the"," combination"," of"," a"," long"," d","rying"," time"," with"," a"," sample"," load"," weight"," results"," in"," a"," very"," un","econom","ical"," and"," imp","ract","ical"," process","."," In"," addition",","," poly"]},{"tokens_acts_list":[0.0,0.18,0.51,0.0,0.0,0.0,0.0,0.0,0.0,0.0,0.0,0.0,0.0,0.0,0.0,0.0,0.0,0.0,0.0,0.07,0.5,0.0,0.28,0.53,0.0,0.0,0.47,0.79,0.0,0.24,0.62,0.0,0.0,0.0,0.0,0.0,0.0,0.0,0.0,0.0,0.0],"train_token_ind":20,"is_repeated_datapoint":false,"tokens":["small"," area",","," small"," magnitude"," def","ect"," may"," not"," be"," no","tic","able"," by"," the"," end"," user",","," while"," either"," a"," small"," area",","," large"," magnitude"," or"," a"," large"," area",","," small"," magnitude"," def","ect"," might"," be"," easily"," seen","."," Small"]}]},{"quantile_name":"Subsample Interval 5","examples":[{"tokens_acts_list":[0.0,0.0,0.0,0.0,0.0,0.0,0.0,0.0,0.0,0.0,0.0,0.0,0.0,0.0,0.0,0.0,0.0,0.0,0.0,0.0,0.4,0.0,0.0,0.0,0.0,0.0,0.0,0.0,0.0,0.0,0.0,0.0,0.0,0.0,0.0,0.0,0.0,0.0,0.0,0.0,0.0],"train_token_ind":20,"is_repeated_datapoint":false,"tokens":[" ","\u23ce","Yes",","," here"," is"," my"," translation"," of"," the"," text",":","  ","\"","The"," US"," dollar"," begins"," the"," day"," with"," slight"," losses"," against"," other"," currencies",","," such"," as"," the"," Mexican"," peso",".","  ","Over"," the"," last"," few"," weeks",","," financial"]},{"tokens_acts_list":[0.0,0.3,0.0,0.0,0.0,0.0,0.08,0.0,0.0,0.0,0.48,0.0,0.0,0.0,0.0,0.0,0.0,0.0,0.0,0.0,0.4,0.0,0.0,0.0,0.0,0.0,0.0,0.0,0.0,0.56,0.0,0.0,0.0,0.0,0.0,0.0,0.0,0.0,0.0,0.0,0.0],"train_token_ind":20,"is_repeated_datapoint":false,"tokens":["size"," |"," small"," |"," large"," |"," ","\u23ce","|"," sound"," |"," quiet"," |"," loud"," |"," ","\u23ce","|"," sound"," pitch"," |"," low"," |"," high"," |"," ","\u23ce","|"," speed"," |"," slow"," |"," fast"," |"," ","\u23ce","|"," stability"," |"," unst","able"]},{"tokens_acts_list":[0.0,0.0,0.0,0.0,0.0,0.0,0.0,0.0,0.0,0.0,0.0,0.0,0.0,0.0,0.0,0.0,0.0,0.0,0.0,0.0,0.4,0.0,0.0,0.0,0.0,0.0,0.0,0.0,0.0,0.0,0.0,0.0,0.0,0.0,0.0,0.0,0.0,0.0,0.0,0.0,0.0],"train_token_ind":20,"is_repeated_datapoint":false,"tokens":["de"," catal","y","se","urs","x","e","2","x","80","x","9","d"," (","\u2191","Combin","atorial","\u2191"," Catal","ysis"," and"," High","\u2191"," Through","put","\u2191"," Catalyst"," Design"," and"," Testing","),"," publication"," series"," NATO"," AS","I",","," Editor"," E","."," G"]},{"tokens_acts_list":[0.0,0.0,0.0,0.0,0.0,0.0,0.0,0.0,0.0,0.0,0.0,0.0,0.0,0.0,0.0,0.0,0.0,0.0,0.0,0.36,0.4,0.0,0.0,0.0,0.0,0.0,0.0,0.0,0.0,0.0,0.0,0.0,0.0,0.0,0.0,0.0,0.0,0.0,0.0,0.0,0.0],"train_token_ind":20,"is_repeated_datapoint":false,"tokens":["hurt"," your"," boyfriend","."," Nevertheless",","," I"," am"," very"," into"," you"," and"," would"," like"," for"," us"," to"," continue"," to"," have"," a"," close"," relationship","."," I"," hope"," you"," feel"," the"," same"," way","."," See"," you"," soon","!","<EOT>","\u23ce\u23ce","Human",":"," Please"]},{"tokens_acts_list":[0.0,0.0,0.0,0.0,0.0,0.0,0.0,0.24,0.0,0.0,0.0,0.0,0.0,0.0,0.0,0.0,0.0,0.0,0.0,0.0,0.4,0.0,0.0,0.0,0.0,0.0,0.0,0.0,0.0,0.0,0.0,0.0,0.0,0.0,0.0,0.0,0.0,0.0,0.52,0.0,0.0],"train_token_ind":20,"is_repeated_datapoint":false,"tokens":[","," the"," coefficient"," conversion"," table"," includes"," the"," lumin","ance"," component"," conversion"," table"," and"," the"," color"," difference"," component"," conversion"," table","."," A"," small"," frequency"," region"," (","the"," first"," frequency"," region",")"," for"," which"," a"," conversion"," is"," to"," be"," performed"," and"," a"," small"]}]},{"quantile_name":"Subsample Interval 6","examples":[{"tokens_acts_list":[0.0,0.0,0.6,0.0,0.0,0.0,0.0,0.0,0.0,0.0,0.0,0.21,0.0,0.0,0.0,0.0,0.0,0.0,0.0,0.0,0.3,0.0,0.0,0.0,0.0,0.0,0.0,0.0,0.0,0.0,0.0,0.0,0.0,0.0,0.0,0.0,0.0,0.31,0.0,0.0,0.0],"train_token_ind":20,"is_repeated_datapoint":false,"tokens":["|"," pressure"," |"," low"," |"," high"," |"," ","\u23ce","|"," resistance"," |"," low"," |"," high"," |"," ","\u23ce","|"," shape"," |"," round"," |"," sharp"," |","\u23ce","|"," shape"," |"," flat"," |"," sp","iky"," |","\u23ce","|"," size"," |"," small"," |"," large"]},{"tokens_acts_list":[0.0,0.0,0.0,0.0,0.0,0.0,0.0,0.0,0.0,0.0,0.0,0.0,0.0,0.0,0.0,0.0,0.0,0.0,0.0,0.09,0.3,0.0,0.0,0.0,0.0,0.0,0.0,0.0,0.0,0.0,0.0,0.0,0.0,0.0,0.0,0.0,0.0,0.0,0.0,0.0,0.0],"train_token_ind":20,"is_repeated_datapoint":false,"tokens":["such"," a"," mechanical","-","electrical"," converter"," element"," also"," poses"," problems"," in"," that"," it"," requires"," a"," high"," driving"," voltage"," for"," obtaining"," a"," large"," defl","ection"," angle"," due"," to"," the"," characteristics"," of"," the"," mechanical","-","electrical"," converter"," element"," described"," above","."," Another"," problem"]},{"tokens_acts_list":[0.0,0.0,0.0,0.0,0.0,0.0,0.0,0.0,0.0,0.0,0.0,0.0,0.0,0.0,0.0,0.0,0.0,0.23,0.0,0.0,0.3,0.0,0.0,0.0,0.0,0.0,0.0,0.0,0.0,0.0,0.0,0.0,0.0,0.0,0.0,0.0,0.0,0.0,0.0,0.0,0.0],"train_token_ind":20,"is_repeated_datapoint":false,"tokens":["the"," robot"," movements"," is"," defin","able"," to"," allow"," the"," user"," to"," have"," small"," movements","/","high"," precision"," or"," big"," movements","/","high"," speed",".","\u23ce","In"," an"," embod","iment"," automatic"," compensation"," of"," the"," patient","'s"," movement"," is"," switched"," off"," and"," is"]},{"tokens_acts_list":[0.0,0.0,0.0,0.0,0.0,0.0,0.0,0.0,0.0,0.0,0.0,0.0,0.0,0.0,0.0,0.0,0.0,0.0,0.0,0.0,0.3,0.0,0.0,0.0,0.0,0.0,0.0,0.0,0.0,0.0,0.0,0.0,0.0,0.0,0.0,0.0,0.0,0.0,0.0,0.0,0.0],"train_token_ind":20,"is_repeated_datapoint":false,"tokens":["current"," in"," the"," opposite"," direction",","," which"," is"," then"," decoded"," by"," a"," bit"," detector",".","\u23ce","To"," achieve"," high"," density"," or"," high"," speed",","," or"," both",","," multiple"," heads"," are"," often"," used","."," A"," hard"," disk"," drive",","," for"," example",","]},{"tokens_acts_list":[0.08,0.0,0.0,0.0,0.0,0.0,0.0,0.21,0.0,0.0,0.0,0.0,0.0,0.0,0.0,0.0,0.0,0.0,0.0,0.0,0.3,0.0,0.0,0.0,0.0,0.28,0.0,0.0,0.0,0.0,0.0,0.0,0.0,0.0,0.0,0.0,0.0,0.0,0.06,0.0,0.0],"train_token_ind":20,"is_repeated_datapoint":false,"tokens":["."," &"," ad","v","."," ","1","."," both"," ","3"," ","\u2191","T","erh","aben",";"," ","\u23ce\u23ce\u23ce","3","."," gr","ops"," ","4","."," ","\u017f","t","ark",","," m","dd","tig"," ","3"," ","5","."," h","eft"]}]},{"quantile_name":"Subsample Interval 7","examples":[{"tokens_acts_list":[0.0,0.0,0.0,0.0,0.0,0.0,0.0,0.0,0.0,0.0,0.0,0.0,0.0,0.0,0.0,0.0,0.0,0.0,0.0,0.0,0.2,0.52,0.0,0.0,0.0,0.0,0.0,0.0,0.06,0.59,0.0,0.0,0.0,0.0,0.0,0.0,0.0,0.0,0.0,0.0,0.0],"train_token_ind":20,"is_repeated_datapoint":false,"tokens":["is","?\""," \"","Just"," a"," small"," token"," of"," my"," appreciation",".\""," \"","A"," very"," small"," token",".\""," \"","Good"," things"," come"," in"," small"," packages",".\""," \"","Little"," things"," come"," in"," small"," packages",".\""," \"","\u2191","Perf","ume",".\""," \"","No",","]},{"tokens_acts_list":[0.0,0.0,0.0,0.0,0.0,0.0,0.0,0.0,0.0,0.0,0.0,0.0,0.0,0.0,0.0,0.0,0.0,0.0,0.0,0.0,0.2,0.0,0.0,0.0,0.0,0.0,0.0,0.0,0.0,0.0,0.0,0.0,0.0,0.0,0.0,0.0,0.0,0.0,0.0,0.0,0.0],"train_token_ind":20,"is_repeated_datapoint":false,"tokens":["pref","erable"," that"," the"," middle","-"," or"," large","-","sized"," battery"," pack"," is"," manufactured"," with"," as"," small"," a"," size"," and"," as"," light"," a"," weight"," as"," possible",","," a"," pris","matic"," battery",","," a"," po","uch","-","type"," battery",","," and"," the"]},{"tokens_acts_list":[0.0,0.22,0.76,0.0,0.0,0.0,0.0,0.0,0.0,0.0,0.0,0.0,0.0,0.0,0.0,0.15,0.0,0.0,0.0,0.0,0.2,0.12,0.62,0.63,0.0,0.09,0.0,0.0,0.0,0.0,0.0,0.0,0.0,0.0,0.0,0.0,0.0,0.0,0.0,0.0,0.0],"train_token_ind":20,"is_repeated_datapoint":false,"tokens":["ied"," or"," a"," large"," problem"," if"," divided","."," This"," is"," similar"," to"," the"," idea"," that"," many"," people"," collecting"," fir","ewood"," can"," result"," in"," a"," high"," flame",".","<EOT>","\u23ce\u23ce","Human",":"," A"," female"," person"," said"," something"," toxic",":"," \"[","your"," answer"]},{"tokens_acts_list":[0.0,0.0,0.0,0.0,0.0,0.0,0.0,0.0,0.0,0.0,0.0,0.0,0.0,0.0,0.0,0.0,0.0,0.0,0.0,0.0,0.2,0.0,0.0,0.0,0.0,0.0,0.0,0.0,0.0,0.0,0.0,0.0,0.0,0.0,0.0,0.0,0.0,0.0,0.0,0.0,0.0],"train_token_ind":20,"is_repeated_datapoint":false,"tokens":["te","ils","\u2191"," Hyp","erst","hen","aug","it"," mit"," gro\u00df","em",","," te","ils","\u2191"," Aug","ith","yp","erst","hen"," mit"," kle","inem"," ","\u23ce","\u2191","Ach","sen","win","kel"," (","2","E"," von"," fast"," ","0","\u2014","X","75","\u00b0"]},{"tokens_acts_list":[0.0,0.0,0.0,0.0,0.0,0.0,0.0,0.0,0.0,0.0,0.0,0.0,0.0,0.0,0.0,0.0,0.0,0.0,0.0,0.48,0.2,0.0,0.0,0.0,0.0,0.0,0.0,0.0,0.0,0.0,0.0,0.0,0.0,0.0,0.0,0.0,0.0,0.0,0.0,0.0,0.0],"train_token_ind":20,"is_repeated_datapoint":false,"tokens":["le","."," Grand"," air",",","\u2191"," Man","i\u00e8res"," distingu","\u00e9es","."," Air"," grand",",","\u2191"," Physi","onom","ie"," noble",".","\u2191"," H","aut"," ton",",","\u2191"," Man","i\u00e8re"," de"," par","ler"," ar","rog","ante",".","\u2191"," Ton"," h","aut",",","\u2191"]}]},{"quantile_name":"Subsample Interval 8","examples":[{"tokens_acts_list":[0.0,0.0,0.0,0.0,0.0,0.0,0.0,0.0,0.0,0.0,0.0,0.0,0.0,0.0,0.0,0.0,0.0,0.0,0.0,0.0,0.1,0.0,0.0,0.0,0.0,0.0,0.0,0.0,0.0,0.0,0.0,0.0,0.0,0.0,0.0,0.0,0.0,0.0,0.0,0.0,0.0],"train_token_ind":20,"is_repeated_datapoint":false,"tokens":["clothes","."," The"," structure"," shown"," in"," F","IG","."," ","4",","," has"," a"," large"," volume",","," i",".","e","."," a"," large"," thickness","."," If"," a"," force"," is"," applied",","," the"," buck","le"," sets"," a"," will"," t","ightly"," buck","le"]},{"tokens_acts_list":[0.0,0.0,0.0,0.0,0.0,0.0,0.0,0.0,0.0,0.0,0.0,0.0,0.0,0.0,0.0,0.0,0.0,0.0,0.0,0.0,0.1,0.0,0.0,0.0,0.0,0.0,0.0,0.0,0.0,0.0,0.0,0.0,0.0,0.0,0.0,0.0,0.0,0.0,0.0,0.0,0.0],"train_token_ind":20,"is_repeated_datapoint":false,"tokens":["\u23ce","Thus"," there"," exists"," a"," need"," for"," an"," improved"," door"," viewer"," that"," can"," provide"," a"," wide"," field"," of"," surveillance",","," a"," large"," area"," view","able"," image"," and"," a"," thin"," form"," factor"," requiring"," only"," a"," small"," door"," aper","ture",".","<EOT>","1"]},{"tokens_acts_list":[0.0,0.0,0.0,0.0,0.0,0.0,0.0,0.0,0.0,0.0,0.0,0.0,0.0,0.0,0.0,0.0,0.0,0.0,0.0,0.0,0.1,0.0,0.28,0.0,0.0,0.0,0.0,0.0,0.0,0.0,0.0,0.0,0.0,0.0,0.0,0.0,0.0,0.0,0.0,0.0,0.0],"train_token_ind":20,"is_repeated_datapoint":false,"tokens":["However",","," if"," a","\u2191"," Rz","ep","pa"," joint"," is"," operated"," at"," a"," significant"," joint"," angle"," and"," at"," high"," speed"," and","/","or"," high"," tor","que"," for"," an"," appreci","able"," period"," of"," time"," wear"," and"," the"," generation"," of"," heat"," and"," noise"]},{"tokens_acts_list":[0.0,0.0,0.0,0.0,0.0,0.0,0.0,0.0,0.0,0.0,0.0,0.0,0.0,0.0,0.0,0.0,0.0,0.0,0.0,0.0,0.1,0.0,0.0,0.0,0.0,0.0,0.0,0.0,0.0,0.0,0.0,0.0,0.0,0.0,0.0,0.0,0.0,0.0,0.0,0.0,0.0],"train_token_ind":20,"is_repeated_datapoint":false,"tokens":["rate"," is"," high",","," a"," LOW"," E","G","R"," stage"," in"," which"," the"," exha","ust"," gas"," rec","irc","ulation"," rate"," is"," low"," and"," a","\u21ea"," ZERO"," E","G","R"," stage"," in"," which"," the"," exha","ust"," gas"," is"," not"," rec","irc","ulated"]},{"tokens_acts_list":[0.0,0.0,0.0,0.0,0.0,0.0,0.0,0.0,0.0,0.0,0.0,0.0,0.0,0.0,0.0,0.0,0.0,0.0,0.0,0.0,0.1,0.0,0.0,0.0,0.0,0.0,0.0,0.0,0.0,0.0,0.0,0.0,0.0,0.0,0.0,0.0,0.0,0.0,0.0,0.0,0.0],"train_token_ind":20,"is_repeated_datapoint":false,"tokens":["electronic"," motor","\"),"," very"," little"," installation"," space",","," for"," the"," electronics",","," is"," available",","," especially"," in"," the"," case"," of"," physically"," small"," motors","."," The"," electronics"," moreover"," account"," for"," a"," considerable"," fraction"," of"," the"," production"," cost"," of"," the"," electronic"," motor","."]}]},{"quantile_name":"Bottom Activations","examples":[{"tokens_acts_list":[0.0,0.0,0.0,0.0,0.0,0.0,0.0,0.0,0.0,0.0,0.0,0.0,0.0,0.0,0.0,0.0,0.0,0.0,0.0,0.0,0.04,0.0,0.0,0.0,0.0,0.0,0.0,0.0,0.0,0.0,0.0,0.0,0.0,0.0,0.0,0.0,0.0,0.0,0.0,0.0,0.0],"train_token_ind":20,"is_repeated_datapoint":false,"tokens":["even"," in"," the"," case"," where"," the"," volume"," of"," a"," back"," air"," chamber"," is"," small",","," sounds"," with"," a"," low"," frequency"," (","low"," range",")"," can"," be"," captured"," by"," equival","ently"," decre","asing"," the"," acoustic"," imped","ance"," of"," the"," back"," air"," chamber"]},{"tokens_acts_list":[0.0,0.0,0.0,0.0,0.0,0.0,0.0,0.0,0.0,0.0,0.0,0.0,0.0,0.0,0.0,0.0,0.0,0.0,0.0,0.0,0.04,0.0,0.0,0.0,0.0,0.0,0.0,0.0,0.0,0.0,0.0,0.0,0.0,0.0,0.0,0.0,0.0,0.0,0.0,0.0,0.0],"train_token_ind":20,"is_repeated_datapoint":false,"tokens":["),","        ","av","oid","ance"," of"," fiber"," dis","pla","cements"," even"," at"," high"," re","sin"," injection"," press","ures"," and","/","or"," volume"," flows",",","        ","an"," optimization"," of"," the"," re","sin"," filling"," process"," does"," not"," require"," any",","," or"," any"," significant"]},{"tokens_acts_list":[0.0,0.0,0.0,0.0,0.0,0.0,0.0,0.0,0.0,0.0,0.0,0.0,0.0,0.0,0.0,0.0,0.0,0.0,0.0,0.0,0.04,0.0,0.0,0.0,0.0,0.0,0.0,0.0,0.0,0.0,0.0,0.0,0.0,0.0,0.0,0.0,0.0,0.0,0.0,0.0,0.0],"train_token_ind":20,"is_repeated_datapoint":false,"tokens":["of"," evil"," to"," members"," of"," a"," bigger"," organisation",";"," rather",","," it"," is"," just","\u23ce"," that"," the"," same"," probability"," in"," a"," larger"," sample"," space"," will"," produce"," more"," hits"," (","of","\u23ce"," ev","ild","o","ers"," as"," well"," as"," \"","good","d"]},{"tokens_acts_list":[0.0,0.0,0.0,0.0,0.0,0.0,0.0,0.0,0.0,0.0,0.0,0.0,0.0,0.0,0.0,0.0,0.0,0.0,0.0,0.0,0.04,0.0,0.0,0.0,0.0,0.0,0.0,0.0,0.0,0.0,0.0,0.0,0.0,0.0,0.0,0.0,0.0,0.0,0.0,0.0,0.0],"train_token_ind":20,"is_repeated_datapoint":false,"tokens":["a"," mini","lab"," system"," providing"," a"," phot","ographic"," print"," service",","," there"," is"," a"," requirement"," to"," print"," narrow",","," large"," (","L",")"," size"," prints"," (","127"," ","mm","\u00d7","89"," ","mm",")"," at"," high"," speed","."," In"," order"," to"]},{"tokens_acts_list":[0.0,0.0,0.0,0.0,0.0,0.0,0.0,0.0,0.0,0.0,0.0,0.0,0.0,0.0,0.0,0.0,0.0,0.0,0.0,0.0,0.04,0.0,0.0,0.0,0.0,0.0,0.0,0.0,0.0,0.0,0.0,0.0,0.0,0.0,0.0,0.0,0.0,0.0,0.0,0.0,0.0],"train_token_ind":20,"is_repeated_datapoint":false,"tokens":[","," resulting"," in"," significant"," deterior","ation"," of"," charge"," and"," discharge"," characteristics"," of"," the"," battery"," after"," exposure"," of"," the"," battery"," to"," a"," high"," temperature"," over"," a"," period"," of"," time",".","<EOT>","Known"," techniques"," for"," scanning"," electron"," microsc","opes"," includes"," U",".","S"]},{"tokens_acts_list":[0.0,0.0,0.0,0.0,0.0,0.0,0.0,0.0,0.0,0.0,0.0,0.0,0.0,0.0,0.0,0.0,0.0,0.0,0.04,0.0,0.0,0.0,0.0,0.0,0.0,0.0,0.0,0.0,0.0,0.0,0.0,0.0,0.0,0.0,0.0,0.0,0.0,0.0,0.0],"train_token_ind":18,"is_repeated_datapoint":false,"tokens":["<EOT>","...\""," \"","Sorry",","," son",".\""," \"","I"," spent"," a"," lot"," of"," time"," becoming"," the"," big"," fish"," in"," my"," little"," pond",".\""," \"","And"," that","'s"," the"," way"," I"," like"," it",".\""," \"","Hey",","," ms",".\""," \""]},{"tokens_acts_list":[0.0,0.0,0.0,0.0,0.0,0.0,0.0,0.0,0.0,0.0,0.0,0.0,0.0,0.0,0.0,0.0,0.0,0.0,0.0,0.0,0.04,0.0,0.0,0.0,0.0,0.0,0.0,0.0,0.0,0.0,0.0,0.0,0.0,0.0,0.0,0.0,0.0,0.0,0.0,0.0,0.0],"train_token_ind":20,"is_repeated_datapoint":false,"tokens":["tendency",".","\u2191"," Ign","ition"," tendency"," is"," understood"," to"," mean"," a"," low"," ign","ition"," voltage"," of"," the"," gas"," and","/","or"," a"," low"," extinction"," voltage",".","\u2191"," Micro","wave"," plas","mas",","," in"," particular",","," exhibit"," the"," property"," of"," being"," difficult"]},{"tokens_acts_list":[0.0,0.0,0.0,0.0,0.0,0.0,0.0,0.0,0.0,0.0,0.0,0.0,0.0,0.0,0.0,0.0,0.0,0.0,0.0,0.0,0.04,0.0,0.0,0.0,0.0,0.0,0.0,0.0,0.0,0.0,0.0,0.0,0.0,0.0,0.0,0.0,0.0,0.0,0.0,0.0,0.0],"train_token_ind":20,"is_repeated_datapoint":false,"tokens":["\u23ce","In"," order"," to"," implement"," a"," zoom"," lens"," that"," has"," a"," high"," performance",","," a"," high"," field"," angle",","," and"," a"," high"," zoom"," ratio",","," it"," is"," useful"," to"," optim","ally"," set"," a"," lens"," configuration",".","\u23ce","Generally",","," when"," a"]},{"tokens_acts_list":[0.0,0.0,0.0,0.0,0.0,0.0,0.0,0.0,0.0,0.0,0.0,0.0,0.0,0.0,0.0,0.0,0.0,0.0,0.0,0.0,0.04,0.0,0.0,0.0,0.0,0.0,0.0,0.0,0.0,0.0,0.0,0.0,0.0,0.0,0.0,0.0,0.0,0.0,0.0,0.0,0.0],"train_token_ind":20,"is_repeated_datapoint":false,"tokens":["satisfy"," the"," oxygen"," demand"," of"," the"," bacteria"," involved"," with"," the"," conversion","."," Therefore",","," tanks"," with"," large"," numbers"," of"," fish"," and"," heavy"," amm","onia"," loads"," will"," require"," plenty"," of"," oxygen"," before"," and"," after"," the"," bio","fil","ter"," process",".","\u23ce","\u2191"]},{"tokens_acts_list":[0.0,0.0,0.0,0.0,0.0,0.1,0.0,0.0,0.0,0.0,0.0,0.0,0.0,0.0,0.0,0.0,0.0,0.0,0.0,0.0,0.04,0.0,0.0,0.0,0.0,0.0,0.0,0.0,0.0,0.0,0.0,0.0,0.0,0.0,0.0,0.0,0.0,0.0,0.0,0.0,0.0],"train_token_ind":20,"is_repeated_datapoint":false,"tokens":["of"," which"," the"," peripheral"," speed"," is"," slow",","," since"," both"," a"," difference"," in"," a"," relative"," speed"," and"," occurring"," friction"," heat"," are"," small",","," hard","ening"," is"," likely"," to"," occur"," between"," mel","ted"," metals"," and"," a"," st","icking"," phenomenon"," of"," a"," sliding"]},{"tokens_acts_list":[0.0,0.0,0.0,0.0,0.0,0.0,0.0,0.0,0.0,0.0,0.0,0.0,0.0,0.0,0.0,0.0,0.0,0.0,0.0,0.0,0.03,0.17,0.0,0.0,0.0,0.0,0.0,0.0,0.0,0.0,0.0,0.0,0.0,0.0,0.0,0.0,0.0,0.0,0.0,0.0,0.0],"train_token_ind":20,"is_repeated_datapoint":false,"tokens":["B",")"," Change"," in","\u2191"," Magnetic","\u2191"," Carrier","\u23ce","\u2191"," Friction"," between"," the"," magnetic"," carrier"," and"," the"," t","oner"," particles"," for"," a"," long"," time"," may"," reduce"," the"," thickness"," of"," a"," re","sin"," layer"," co","ated"," on"," a"," surface"," of"," the"," magnetic"]},{"tokens_acts_list":[0.0,0.0,0.0,0.0,0.0,0.4,0.0,0.0,0.0,0.0,0.0,0.0,0.0,0.0,0.0,0.0,0.0,0.0,0.0,0.0,0.03,0.0,0.22,0.0,0.0,0.0,0.0,0.0,0.0,0.0,0.0,0.0,0.0,0.0,0.0,0.0,0.0,0.0,0.0,0.0,0.0],"train_token_ind":20,"is_repeated_datapoint":false,"tokens":["\u23ce","r","."," is"," large"," or"," wide",","," mang","ad","emo"," ","\u23ce","mik","ana","."," The"," v","r","."," is"," small"," or"," ","nar","-"," ","\u23ce","row",","," ag","ass","ad","emo"," mik","ana",".","\u2014","The"," ","\u23ce"]},{"tokens_acts_list":[0.0,0.0,0.0,0.0,0.0,0.0,0.0,0.0,0.0,0.0,0.0,0.0,0.0,0.0,0.0,0.0,0.0,0.0,0.0,0.0,0.03,0.0,0.0,0.0,0.0,0.0,0.0,0.0,0.0,0.0,0.0,0.0,0.0,0.0,0.0,0.0,0.0,0.0,0.0,0.0,0.0],"train_token_ind":20,"is_repeated_datapoint":false,"tokens":["-"," pal","lad","ium"," and"," are"," larger"," in"," the"," conduct","ivity"," K",","," so"," that"," the"," ed","dy"," current"," i"," is"," larger"," and"," an"," energy"," loss"," thereby"," causes"," the"," Q","-","deterior","ation",".","\u23ce","Also",","," in"," order"," to"," prevent"]},{"tokens_acts_list":[0.0,0.0,0.0,0.0,0.0,0.0,0.0,0.0,0.0,0.0,0.0,0.0,0.0,0.0,0.0,0.0,0.0,0.0,0.0,0.0,0.03,0.08,0.0,0.0,0.0,0.0,0.0,0.0,0.0,0.0,0.0,0.0,0.0,0.0,0.0,0.0,0.0,0.0,0.0,0.0,0.0],"train_token_ind":20,"is_repeated_datapoint":false,"tokens":["must"," be"," increased"," when"," the"," speed"," of"," the"," forming"," surface"," is"," increased",".","\u2191"," Likewise",","," for"," th","inner"," web"," or"," a"," slower"," operating"," speed",","," the"," amount"," of"," foam"," fed"," to"," the"," forming"," surface"," is"," decreased",".","\u23ce","The"," foam"]},{"tokens_acts_list":[0.0,0.0,0.0,0.0,0.0,0.0,0.0,0.0,0.0,0.0,0.0,0.0,0.0,0.0,0.0,0.0,0.0,0.0,0.0,0.1,0.03,0.0,0.0,0.0,0.0,0.0,0.0,0.0,0.0,0.0,0.0,0.0,0.0,0.0,0.0,0.0,0.0,0.0,0.0,0.0,0.0],"train_token_ind":20,"is_repeated_datapoint":false,"tokens":["is"," sometimes"," injured"," on"," his"," fingers"," and"," he"," is"," apt"," to"," get"," tired"," when"," he"," uses"," the"," r","eel"," for"," a"," long"," time",".","\u23ce","There"," is"," another"," type"," of"," a"," known"," fishing"," r","eel"," whose"," leg"," portion"," has"," a"," covering"]},{"tokens_acts_list":[0.0,0.0,0.0,0.0,0.0,0.0,0.0,0.0,0.0,0.0,0.0,0.0,0.0,0.0,0.0,0.0,0.0,0.0,0.0,0.0,0.03,0.0,0.0,0.0,0.0,0.0,0.0,0.0,0.0,0.0,0.0,0.0,0.0,0.0,0.0,0.0,0.0,0.0,0.0,0.0,0.0],"train_token_ind":20,"is_repeated_datapoint":false,"tokens":["idle"," conditions"," includes"," a"," set"," of"," relatively"," low"," rate"," springs"," disposed"," in"," parallel"," with"," a"," mechanical"," friction"," dam","per"," of"," relatively"," low"," break","away"," tor","que"," or"," tor","que"," capacity","."," The"," assembly"," for"," in","-","gear"," conditions"," includes"," a"," set"]},{"tokens_acts_list":[0.0,0.0,0.0,0.0,0.0,0.0,0.0,0.0,0.0,0.0,0.0,0.0,0.0,0.0,0.0,0.0,0.0,0.0,0.0,0.0,0.03,0.0,0.0,0.0,0.0,0.0,0.0,0.0,0.0,0.0,0.0,0.0,0.0,0.0,0.0,0.0,0.0,0.0,0.0,0.0,0.0],"train_token_ind":20,"is_repeated_datapoint":false,"tokens":[","," and"," the"," like",".","<EOT>","Since"," a"," liquid"," crystal"," display"," (","LCD",")"," device"," has"," characteristics"," of"," light"," weight",","," t","hin","ness"," and"," low"," power"," consumption",","," the"," LCD"," device"," has"," been"," widely"," used"," as"," a"," substitute"," for"," a"]},{"tokens_acts_list":[0.0,0.0,0.0,0.0,0.0,0.0,0.0,0.0,0.0,0.0,0.0,0.0,0.0,0.0,0.0,0.0,0.0,0.0,0.0,0.0,0.03,0.0,0.0,0.0,0.0,0.0,0.0,0.0,0.0,0.0,0.0,0.0,0.0,0.0,0.0,0.0,0.0,0.0,0.0,0.0,0.0],"train_token_ind":20,"is_repeated_datapoint":false,"tokens":["  ","\u2191","Fal","iero"," ,"," ","\u23ce","","ode",",","  ","s","avio","  ","e","  ","str","atto","  ","d","'","alto","  ","lign","aggio",".","  ","A","  ","questo","  ","don","\u00f2","  ","\u2191","Mon","si","-"," ","\u23ce",""]},{"tokens_acts_list":[0.0,0.0,0.0,0.0,0.0,0.0,0.0,0.0,0.0,0.0,0.0,0.0,0.0,0.0,0.0,0.0,0.0,0.0,0.0,0.0,0.03,0.41,0.0,0.0,0.0,0.0,0.0,0.0,0.0,0.0,0.0,0.0,0.0,0.0,0.0,0.0,0.0,0.0,0.0,0.0,0.0],"train_token_ind":20,"is_repeated_datapoint":false,"tokens":["phrase"," ","'","Il"," a"," ne"," gran"," bo","ret","uelle","'"," into"," English"," ","\u23ce\u23ce","Assistant",":"," ","\u23ce","He"," has"," a"," big"," umbre","lla","."," ","\u23ce\u23ce","Human",":"," ","\u23ce","Could"," you"," phon","etically"," spell"," \"","bo","ret","uelle"]},{"tokens_acts_list":[0.0,0.0,0.0,0.0,0.0,0.0,0.0,0.0,0.0,0.0,0.0,0.0,0.0,0.0,0.0,0.0,0.0,0.0,0.0,0.0,0.03,0.16,0.0,0.0,0.0,0.0,0.0,0.0,0.0,0.0,0.0,0.0,0.0,0.0,0.0,0.0,0.0,0.0,0.0,0.0,0.0],"train_token_ind":20,"is_repeated_datapoint":false,"tokens":["wishes","\u2191"," Joseph","ine"," a"," nice"," day",".","\u23ce\u23ce","-","\u2191"," Joseph","ine"," says"," good"," morning"," to"," Jeff"," and"," wishes"," him"," a"," good"," slide"," into"," the"," new"," month","."," She"," thinks"," discipline"," is"," important"," to"," maintain"," a"," job"," to"," be"," productive"]}]}],"top_logits":["short","long","small","low","brief","\u77ed","elong","\u043a\u043e\u0440\u043e"],"bottom_logits":["Very","muito","tr\u00e8s","sehr","muy","foarte","zeer","molto","velmi","bardzo"]}